{
  "id" : "6889e09de079e541d9db85a3",
  "gid" : "01985a95-6586-763f-8728-cdb1ee53fa57",
  "name" : "HuongBA1",
  "applicationType" : 3,
  "applicationStatus" : "NORMAL",
  "editingApplicationDSL" : {
    "ui" : {
      "comp" : {
        "dataOptionType" : "manual",
        "items" : [ ],
        "jsonItems" : "[]",
        "width" : "240",
        "backgroundImage" : "",
        "mode" : "vertical"
      },
      "compType" : "navV2_VNPT"
    },
    "refTree" : {
      "value" : ""
    },
    "hooks" : [ {
      "compType" : "urlParams",
      "comp" : { },
      "name" : "url"
    }, {
      "compType" : "dayJsLib",
      "comp" : { },
      "name" : "dayjs"
    }, {
      "compType" : "lodashJsLib",
      "comp" : { },
      "name" : "_"
    }, {
      "compType" : "utils",
      "comp" : { },
      "name" : "utils"
    }, {
      "compType" : "message",
      "comp" : { },
      "name" : "message"
    }, {
      "compType" : "toast",
      "comp" : { },
      "name" : "toast"
    }, {
      "compType" : "localStorage",
      "comp" : { },
      "name" : "localStorage"
    }, {
      "compType" : "currentUser",
      "comp" : { },
      "name" : "currentUser"
    }, {
      "compType" : "screenInfo",
      "comp" : { },
      "name" : "screenInfo"
    }, {
      "compType" : "theme",
      "comp" : { },
      "name" : "theme"
    } ],
    "settings" : {
      "title" : "",
      "description" : "",
      "category" : "Business",
      "showHeaderInPublic" : false,
      "themeId" : "default",
      "preventAppStylesOverwriting" : true,
      "disableCollision" : false,
      "lowcoderCompVersion" : "latest",
      "maxWidth" : {
        "dropdown" : "1920",
        "input" : 0
      },
      "gridRowCount" : "Infinity",
      "gridPaddingX" : "20",
      "gridPaddingY" : "20"
    },
    "preload" : {
      "script" : "",
      "css" : "",
      "globalCSS" : ""
    },
    "pages" : [ ]
  },
  "publicToAll" : false,
  "publicToMarketplace" : false,
  "agencyProfile" : false,
  "editingUserId" : "",
  "lastEditedAt" : "2025-07-30T09:06:37.062Z",
  "createdAt" : "2025-07-30T09:06:37.068Z",
  "changeType" : "NONE",
  "updatedAt" : "2025-08-01T03:00:36.533Z",
  "createdBy" : "686b37008543551b717cb6ab",
  "slug" : null,
  "organizationId" : "6858c3d55977a424158e6a91",
  "commitId" : "git-344afb07-21b9-4346-9722-e70ed3a0b95f",
  "lastCommitAt" : "2025-08-01T03:00:36.533Z",
  "editingQueries" : [ ],
  "editingModules" : [ ],
  "editingApplicationDSLOrNull" : {
    "ui" : {
      "comp" : {
        "dataOptionType" : "manual",
        "items" : [ ],
        "jsonItems" : "[]",
        "width" : "240",
        "backgroundImage" : "",
        "mode" : "vertical"
      },
      "compType" : "navV2_VNPT"
    },
    "refTree" : {
      "value" : ""
    },
    "hooks" : [ {
      "compType" : "urlParams",
      "comp" : { },
      "name" : "url"
    }, {
      "compType" : "dayJsLib",
      "comp" : { },
      "name" : "dayjs"
    }, {
      "compType" : "lodashJsLib",
      "comp" : { },
      "name" : "_"
    }, {
      "compType" : "utils",
      "comp" : { },
      "name" : "utils"
    }, {
      "compType" : "message",
      "comp" : { },
      "name" : "message"
    }, {
      "compType" : "toast",
      "comp" : { },
      "name" : "toast"
    }, {
      "compType" : "localStorage",
      "comp" : { },
      "name" : "localStorage"
    }, {
      "compType" : "currentUser",
      "comp" : { },
      "name" : "currentUser"
    }, {
      "compType" : "screenInfo",
      "comp" : { },
      "name" : "screenInfo"
    }, {
      "compType" : "theme",
      "comp" : { },
      "name" : "theme"
    } ],
    "settings" : {
      "title" : "",
      "description" : "",
      "category" : "Business",
      "showHeaderInPublic" : false,
      "themeId" : "default",
      "preventAppStylesOverwriting" : true,
      "disableCollision" : false,
      "lowcoderCompVersion" : "latest",
      "maxWidth" : {
        "dropdown" : "1920",
        "input" : 0
      },
      "gridRowCount" : "Infinity",
      "gridPaddingX" : "20",
      "gridPaddingY" : "20"
    },
    "preload" : {
      "script" : "",
      "css" : "",
      "globalCSS" : ""
    },
    "pages" : [ ]
  }
}